{
    "/js/app.js": "/js/app.js",
    "/js/app.6b34a5546d979dcce670.hot-update.js": "/js/app.6b34a5546d979dcce670.hot-update.js",
    "/js/app.c925d55309087565d177.hot-update.js": "/js/app.c925d55309087565d177.hot-update.js",
    "/js/app.6e540d842f397f2fcb1e.hot-update.js": "/js/app.6e540d842f397f2fcb1e.hot-update.js",
    "/js/app.ca363baf0c3cf41725e6.hot-update.js": "/js/app.ca363baf0c3cf41725e6.hot-update.js",
    "/js/app.81bdc02a636c363d3f93.hot-update.js": "/js/app.81bdc02a636c363d3f93.hot-update.js",
    "/js/app.5ad71f54e6ed24c570c9.hot-update.js": "/js/app.5ad71f54e6ed24c570c9.hot-update.js",
    "/js/app.53ac4a552f0cceada32c.hot-update.js": "/js/app.53ac4a552f0cceada32c.hot-update.js",
    "/js/app.426473d9622cc435202e.hot-update.js": "/js/app.426473d9622cc435202e.hot-update.js",
    "/js/app.a1ee44141bb22f4d4cb3.hot-update.js": "/js/app.a1ee44141bb22f4d4cb3.hot-update.js",
    "/js/app.5b89fad1d8a07615676e.hot-update.js": "/js/app.5b89fad1d8a07615676e.hot-update.js",
    "/js/app.dd89a39f4e887b904356.hot-update.js": "/js/app.dd89a39f4e887b904356.hot-update.js",
    "/js/app.34ab7af05287dfe860bb.hot-update.js": "/js/app.34ab7af05287dfe860bb.hot-update.js",
    "/js/app.7649b7e963fd04311f47.hot-update.js": "/js/app.7649b7e963fd04311f47.hot-update.js",
    "/js/app.5f6e273f358d3a6a290d.hot-update.js": "/js/app.5f6e273f358d3a6a290d.hot-update.js",
    "/js/app.cdfdc0796ebcb3ff90d8.hot-update.js": "/js/app.cdfdc0796ebcb3ff90d8.hot-update.js",
    "/js/app.f441ecdcff9a42ef402c.hot-update.js": "/js/app.f441ecdcff9a42ef402c.hot-update.js",
    "/js/app.b2120c4d2c67bc680b57.hot-update.js": "/js/app.b2120c4d2c67bc680b57.hot-update.js",
    "/js/app.94709dbb24be481d3b96.hot-update.js": "/js/app.94709dbb24be481d3b96.hot-update.js",
    "/js/app.845d2541c60a370e2172.hot-update.js": "/js/app.845d2541c60a370e2172.hot-update.js",
    "/js/app.5cc46ad1743985e5cf1e.hot-update.js": "/js/app.5cc46ad1743985e5cf1e.hot-update.js",
    "/js/app.7d514809af2ac70dde38.hot-update.js": "/js/app.7d514809af2ac70dde38.hot-update.js",
    "/js/app.91196830fd09cc92c8ff.hot-update.js": "/js/app.91196830fd09cc92c8ff.hot-update.js",
    "/js/app.47b12960113cf05950ef.hot-update.js": "/js/app.47b12960113cf05950ef.hot-update.js",
    "/js/app.f2e2e6bac2323fffb760.hot-update.js": "/js/app.f2e2e6bac2323fffb760.hot-update.js",
    "/js/app.58130cf6a523ec6ac43e.hot-update.js": "/js/app.58130cf6a523ec6ac43e.hot-update.js",
    "/js/app.79c80cefdd72a5c342a4.hot-update.js": "/js/app.79c80cefdd72a5c342a4.hot-update.js",
    "/js/app.cde8dc0cedbb256e79f8.hot-update.js": "/js/app.cde8dc0cedbb256e79f8.hot-update.js",
    "/js/app.8a5b7e9b692f708ccda2.hot-update.js": "/js/app.8a5b7e9b692f708ccda2.hot-update.js",
    "/js/app.fad0281729c8bcb39f3b.hot-update.js": "/js/app.fad0281729c8bcb39f3b.hot-update.js",
    "/js/app.1e93e1574a231b2121d2.hot-update.js": "/js/app.1e93e1574a231b2121d2.hot-update.js",
    "/js/app.c519d8bdbd331f399d46.hot-update.js": "/js/app.c519d8bdbd331f399d46.hot-update.js",
    "/js/app.3222a68f2233d1a5d2ed.hot-update.js": "/js/app.3222a68f2233d1a5d2ed.hot-update.js",
    "/js/app.dc6228dbe8b9588d8362.hot-update.js": "/js/app.dc6228dbe8b9588d8362.hot-update.js",
    "/js/app.98c925eab4df802ebac6.hot-update.js": "/js/app.98c925eab4df802ebac6.hot-update.js",
    "/js/app.50918df0765e3cb57e69.hot-update.js": "/js/app.50918df0765e3cb57e69.hot-update.js",
    "/js/app.8691e2e5b5bccc6ce30c.hot-update.js": "/js/app.8691e2e5b5bccc6ce30c.hot-update.js",
    "/js/app.342b59a5a46d2ad6e073.hot-update.js": "/js/app.342b59a5a46d2ad6e073.hot-update.js",
    "/js/app.36cb7e92131823b3a103.hot-update.js": "/js/app.36cb7e92131823b3a103.hot-update.js",
    "/js/app.10df260704d5cf5df41e.hot-update.js": "/js/app.10df260704d5cf5df41e.hot-update.js",
    "/js/app.e3278ebb71e8fd7ff714.hot-update.js": "/js/app.e3278ebb71e8fd7ff714.hot-update.js",
    "/js/app.61d4dacf2480c49f8a93.hot-update.js": "/js/app.61d4dacf2480c49f8a93.hot-update.js",
    "/js/app.695cd59deabff6ddb114.hot-update.js": "/js/app.695cd59deabff6ddb114.hot-update.js",
    "/js/app.45d61ff9dfb914f82d27.hot-update.js": "/js/app.45d61ff9dfb914f82d27.hot-update.js",
    "/js/app.76944c2de936af1ecaab.hot-update.js": "/js/app.76944c2de936af1ecaab.hot-update.js"
}
