{
    "/js/app.js": "/js/app.js",
    "/js/app.c4dd09e59c998a773cc3.hot-update.js": "/js/app.c4dd09e59c998a773cc3.hot-update.js",
    "/js/app.96d51316df9216a6162e.hot-update.js": "/js/app.96d51316df9216a6162e.hot-update.js",
    "/js/app.81dda65badb13266edd6.hot-update.js": "/js/app.81dda65badb13266edd6.hot-update.js",
    "/js/app.83bcf58b1d7c2502d8e6.hot-update.js": "/js/app.83bcf58b1d7c2502d8e6.hot-update.js",
    "/js/app.b1a3bf9899e77b505754.hot-update.js": "/js/app.b1a3bf9899e77b505754.hot-update.js",
    "/js/app.51ee306d7387da8790e8.hot-update.js": "/js/app.51ee306d7387da8790e8.hot-update.js",
    "/js/app.8bcc7534d751139b74f1.hot-update.js": "/js/app.8bcc7534d751139b74f1.hot-update.js",
    "/js/app.fa5301f0ef22cc093364.hot-update.js": "/js/app.fa5301f0ef22cc093364.hot-update.js",
    "/js/app.460bf2f685aec05d9ceb.hot-update.js": "/js/app.460bf2f685aec05d9ceb.hot-update.js",
    "/js/app.c57b638419ad69c4d376.hot-update.js": "/js/app.c57b638419ad69c4d376.hot-update.js",
    "/js/app.25306e270f820c0b01ef.hot-update.js": "/js/app.25306e270f820c0b01ef.hot-update.js",
    "/js/app.6a7a81acbaaa630e8263.hot-update.js": "/js/app.6a7a81acbaaa630e8263.hot-update.js",
    "/js/app.f9d4617d87b468ada87d.hot-update.js": "/js/app.f9d4617d87b468ada87d.hot-update.js",
    "/js/app.3555b8a1779c8ad758f0.hot-update.js": "/js/app.3555b8a1779c8ad758f0.hot-update.js",
    "/js/app.85906b1eb94beaa17765.hot-update.js": "/js/app.85906b1eb94beaa17765.hot-update.js",
    "/js/app.b68296b6e0c317118488.hot-update.js": "/js/app.b68296b6e0c317118488.hot-update.js",
    "/js/app.1d638fb3f2cbe3ca27cd.hot-update.js": "/js/app.1d638fb3f2cbe3ca27cd.hot-update.js",
    "/js/app.39a44b24d0faf7b5fedc.hot-update.js": "/js/app.39a44b24d0faf7b5fedc.hot-update.js",
    "/js/app.1cc4b9a1e26ac64464f0.hot-update.js": "/js/app.1cc4b9a1e26ac64464f0.hot-update.js",
    "/js/app.c420cb8e1d6d40ecb300.hot-update.js": "/js/app.c420cb8e1d6d40ecb300.hot-update.js",
    "/js/app.79efd80b47ca2c12670e.hot-update.js": "/js/app.79efd80b47ca2c12670e.hot-update.js",
    "/js/app.1b66e472e4af96a4cb6b.hot-update.js": "/js/app.1b66e472e4af96a4cb6b.hot-update.js",
    "/js/app.66d7e01a497a177a6dd7.hot-update.js": "/js/app.66d7e01a497a177a6dd7.hot-update.js",
    "/js/app.40f772d56019453daba0.hot-update.js": "/js/app.40f772d56019453daba0.hot-update.js",
    "/js/app.ec1a298cfc3e56081ad3.hot-update.js": "/js/app.ec1a298cfc3e56081ad3.hot-update.js",
    "/js/app.202526a87581be76d4fa.hot-update.js": "/js/app.202526a87581be76d4fa.hot-update.js",
    "/js/app.6c93249fca2741a1a4aa.hot-update.js": "/js/app.6c93249fca2741a1a4aa.hot-update.js",
    "/js/app.af1611ccda8b94f2d4af.hot-update.js": "/js/app.af1611ccda8b94f2d4af.hot-update.js",
    "/js/app.6b9a5e78cf937b155b74.hot-update.js": "/js/app.6b9a5e78cf937b155b74.hot-update.js",
    "/js/app.d5e9759a2f74ef19917d.hot-update.js": "/js/app.d5e9759a2f74ef19917d.hot-update.js",
    "/js/app.2cadf78d3b0801a2cd9d.hot-update.js": "/js/app.2cadf78d3b0801a2cd9d.hot-update.js",
    "/js/app.83aa61bf5b7c05457ad0.hot-update.js": "/js/app.83aa61bf5b7c05457ad0.hot-update.js",
    "/js/app.fb6261651aba5dafb425.hot-update.js": "/js/app.fb6261651aba5dafb425.hot-update.js",
    "/js/app.be735f67912b8d22621e.hot-update.js": "/js/app.be735f67912b8d22621e.hot-update.js",
    "/js/app.d55fb84aaf31475eaaec.hot-update.js": "/js/app.d55fb84aaf31475eaaec.hot-update.js",
    "/js/app.f7f465af4eea7391cfae.hot-update.js": "/js/app.f7f465af4eea7391cfae.hot-update.js",
    "/js/app.395b16adddd55bad9916.hot-update.js": "/js/app.395b16adddd55bad9916.hot-update.js",
    "/js/app.4dfb9b49e2b80dea8155.hot-update.js": "/js/app.4dfb9b49e2b80dea8155.hot-update.js",
    "/js/app.f2fcea03ceb79029bfd3.hot-update.js": "/js/app.f2fcea03ceb79029bfd3.hot-update.js",
    "/js/app.9e892cd34a994d5291e2.hot-update.js": "/js/app.9e892cd34a994d5291e2.hot-update.js",
    "/js/app.f48d8a4f2389fefb33e1.hot-update.js": "/js/app.f48d8a4f2389fefb33e1.hot-update.js",
    "/js/app.49133f53c8df49827c6a.hot-update.js": "/js/app.49133f53c8df49827c6a.hot-update.js",
    "/js/app.8d2f25789095a183c0fd.hot-update.js": "/js/app.8d2f25789095a183c0fd.hot-update.js",
    "/js/app.cf5cb389fdc2092ac0af.hot-update.js": "/js/app.cf5cb389fdc2092ac0af.hot-update.js",
    "/js/app.5bf4fa4bde08be52a9dc.hot-update.js": "/js/app.5bf4fa4bde08be52a9dc.hot-update.js",
    "/js/app.333f7c898442995221b5.hot-update.js": "/js/app.333f7c898442995221b5.hot-update.js",
    "/js/app.8868fe8e4b54a1901a73.hot-update.js": "/js/app.8868fe8e4b54a1901a73.hot-update.js",
    "/js/app.94af9066aea499fa48e9.hot-update.js": "/js/app.94af9066aea499fa48e9.hot-update.js"
}
